figurefirst/__init__.py
figurefirst/_backup_deprecated_reproduce.py
figurefirst/deprecated_regenerate.py
figurefirst/figurefirst_user_parameters.py
figurefirst/mpl_fig_to_figurefirst_svg.py
figurefirst/mpl_functions.py
figurefirst/regenerate.py
figurefirst/svg_to_axes.py
figurefirst/svg_util.py
figurefirst-0.0.3.data/data/inkscape_extensions/tag_axis.inx
figurefirst-0.0.3.data/data/inkscape_extensions/tag_axis.py
figurefirst-0.0.3.data/data/inkscape_extensions/tag_figure.inx
figurefirst-0.0.3.data/data/inkscape_extensions/tag_figure.py
figurefirst-0.0.3.data/data/inkscape_extensions/tag_group.inx
figurefirst-0.0.3.data/data/inkscape_extensions/tag_group.py
figurefirst-0.0.3.data/data/inkscape_extensions/tag_linespec.inx
figurefirst-0.0.3.data/data/inkscape_extensions/tag_linespec.py
figurefirst-0.0.3.data/data/inkscape_extensions/tag_mplmethods.inx
figurefirst-0.0.3.data/data/inkscape_extensions/tag_mplmethods.py
figurefirst-0.0.3.data/data/inkscape_extensions/tag_patchspec.inx
figurefirst-0.0.3.data/data/inkscape_extensions/tag_patchspec.py
figurefirst-0.0.3.data/data/inkscape_extensions/tag_spinespec.inx
figurefirst-0.0.3.data/data/inkscape_extensions/tag_spinespec.py
figurefirst-0.0.3.data/data/inkscape_extensions/tag_svgitem.inx
figurefirst-0.0.3.data/data/inkscape_extensions/tag_svgitem.py
figurefirst_scripts/__init__.py
figurefirst_scripts/install_inkscape_ext.py
figurefirst-0.0.3.dist-info/LICENSE.txt
figurefirst-0.0.3.dist-info/METADATA
figurefirst-0.0.3.dist-info/WHEEL
figurefirst-0.0.3.dist-info/entry_points.txt
figurefirst-0.0.3.dist-info/top_level.txt
figurefirst-0.0.3.dist-info/RECORD
