Metadata-Version: 2.1
Name: figurefirst
Version: 0.0.3
Summary: Matplotlib plotting stuff
Home-page: UNKNOWN
Author: Floris van Breugel, Theodore Lindsay, Peter Weir
Author-email: floris@caltech.edu
License: BSD
Platform: UNKNOWN
Requires-Dist: numpy
Requires-Dist: matplotlib
Requires-Dist: dill
Requires-Dist: backports.functools-lru-cache
